ace_upload/__init__.py
ace_upload/__main__.py
ace_upload/_upload.py
ace_upload-1.7.0.dist-info/LICENSE
ace_upload-1.7.0.dist-info/METADATA
ace_upload-1.7.0.dist-info/WHEEL
ace_upload-1.7.0.dist-info/entry_points.txt
ace_upload-1.7.0.dist-info/top_level.txt
ace_upload-1.7.0.dist-info/RECORD
