Metadata-Version: 2.1
Name: ace-upload
Version: 1.7.0
Summary: For uploading documents to brewlytics MinIO
Home-page: https://github.com/Oaklea-Simpson-Security/ACE-C
Author: Oaklea Simpson Security LLC
Author-email: king@oakleasimpsonsecurity.com
License: MIT
Platform: UNKNOWN
Classifier: License :: OSI Approved :: MIT License
Classifier: Programming Language :: Python :: 3
Classifier: Programming Language :: Python :: 3.7
Requires-Dist: minio
Requires-Dist: urllib3
Requires-Dist: requests
Requires-Dist: glob2
Requires-Dist: numpy
